Metadata-Version: 1.0
Name: pyramid-rest
Version: 0.2.8
Summary: Pyramid Rest Extension
Home-page: UNKNOWN
Author: Hadrien David
Author-email: hadrien@ectobal.com
License: UNKNOWN
Platform: UNKNOWN
